<?xml version="1.0" encoding="UTF-8"?>
<!--
     Attention: Generated code! Do not modify by hand!
     Generated by: hibernate.hbm.xml.vsl in andromda-hibernate-cartridge.
  -->
<!DOCTYPE hibernate-mapping PUBLIC "-//Hibernate/Hibernate Mapping DTD 3.0//EN"
          "http://hibernate.sourceforge.net/hibernate-mapping-3.0.dtd">

<hibernate-mapping default-cascade="none">
    <class name="com.oatsystems.udm.logicalHier.ObjectAssnImpl" table="OBJECT_ASSN" dynamic-insert="false" dynamic-update="false">
        <id name="objectAssnID" type="java.lang.Long" unsaved-value="null">
            <column name="OBJECT_ASSN_ID" sql-type="INTEGER"/>
            <generator class="native">
            </generator>
        </id>
        <property name="insertDate" type="java.sql.Timestamp">
            <column name="insert_date" not-null="false" unique="false" sql-type="DATETIME"/>
        </property>
        <property name="updateDate" type="java.sql.Timestamp">
            <column name="update_date" not-null="false" unique="false" sql-type="DATETIME"/>
        </property>
        <property name="LKHashCode" type="java.lang.Long">
            <column name="lk_hashcode" not-null="false" unique="false" sql-type="INTEGER"/>
        </property>
        <property name="deleted" type="true_false">
            <column name="DELETED" not-null="false" unique="false" sql-type="CHAR(1)" default="'F'"/>
        </property>
        <property name="lastUpdateState" type="java.lang.Long">
            <column name="LAST_UPDATE_STATE" not-null="false" unique="false" sql-type="INTEGER"/>
        </property>
        <property name="state" type="java.lang.Long">
            <column name="STATE" not-null="false" unique="false" sql-type="INTEGER"/>
        </property>
        <property name="guid" type="java.lang.String">
            <column name="GUID" not-null="false" unique="false" sql-type="NVARCHAR(255) COLLATE SQL_Latin1_General_CP1_CS_AS"/>
        </property>
        <property name="startTs" type="java.util.Date">
            <column name="START_TS" not-null="false" unique="false" sql-type="DATETIME"/>
        </property>
        <property name="endTs" type="java.util.Date">
            <column name="END_TS" not-null="false" unique="false" sql-type="DATETIME"/>
        </property>
        <property name="bizStep" type="java.lang.String">
            <column name="bizstep" not-null="false" unique="false" sql-type="NVARCHAR(100) COLLATE SQL_Latin1_General_CP1_CS_AS"/>
        </property>
        <property name="disposition" type="java.lang.String">
            <column name="disposition" not-null="false" unique="false" sql-type="NVARCHAR(100) COLLATE SQL_Latin1_General_CP1_CS_AS"/>
        </property>
        <property name="action" type="java.lang.String">
            <column name="action" not-null="false" unique="false" sql-type="NVARCHAR(50) COLLATE SQL_Latin1_General_CP1_CS_AS"/>
        </property>
        <property name="recordTime" type="java.sql.Timestamp">
            <column name="record_time" not-null="false" unique="false" sql-type="DATETIME"/>
        </property>
        <property name="eventTimeZoneOffset" type="java.lang.String">
            <column name="eventTimeZoneOffset" not-null="false" unique="false" sql-type="NVARCHAR(100) COLLATE SQL_Latin1_General_CP1_CS_AS"/>
        </property>
        <property name="lastSeenTime" type="java.util.Date">
            <column name="LAST_SEEN_TIME" not-null="false" unique="false" sql-type="DATETIME"/>
        </property>
        <property name="verificationData0" type="java.lang.String">
            <column name="VERIFICATION_DATA_0" not-null="false" unique="false" sql-type="NVARCHAR(750) COLLATE SQL_Latin1_General_CP1_CS_AS"/>
        </property>
        <property name="tempLastSeenTime" type="java.util.Date">
            <column name="TEMP_LAST_SEEN_TIME" not-null="false" unique="false" sql-type="DATETIME"/>
        </property>
        <many-to-one name="lastSeenProcess" class="com.oatsystems.udm.logicalProcess.ProcessImpl" foreign-key="OBJ_ASSN_FK11" lazy="proxy" fetch="select">
            <column name="LAST_SEEN_PROCESS_ID" not-null="false" sql-type="INTEGER"/>
        </many-to-one>
        <many-to-one name="partner" class="com.oatsystems.udm.partner.PartnerImpl" foreign-key="objassnpartner_fk1" lazy="proxy" fetch="select">
            <column name="partner_id" not-null="false" sql-type="INTEGER"/>
        </many-to-one>
        <many-to-one name="assnTermMethod" class="com.oatsystems.udm.logicalHier.AssnMethodImpl" foreign-key="OBJ_ASSN_FK2" lazy="proxy" fetch="select">
            <column name="ASSN_TERM_METHOD_ID" not-null="false" sql-type="INTEGER"/>
        </many-to-one>
        <many-to-one name="endAssnLocation" class="com.oatsystems.udm.physical.LocationImpl" foreign-key="OBJ_ASSN_FK6" lazy="proxy" fetch="select">
            <column name="END_ASSN_LOCATION_ID" not-null="false" sql-type="INTEGER"/>
        </many-to-one>
        <many-to-one name="parentObject" class="com.oatsystems.udm.logicalObj.LogicalObjectImpl" foreign-key="OBJ_ASSN_FK10" lazy="proxy" fetch="select">
            <column name="PARENT_OBJECT_ID" not-null="false" sql-type="INTEGER"/>
        </many-to-one>
        <many-to-one name="process" class="com.oatsystems.udm.logicalProcess.ProcessImpl" foreign-key="OBJ_ASSN_FK3" lazy="proxy" fetch="select">
            <column name="PROCESS_ID" not-null="false" sql-type="INTEGER"/>
        </many-to-one>
        <many-to-one name="sensewareInstall" class="com.oatsystems.udm.sw.SensewareInstallImpl" foreign-key="OBJ_ASSN_FK8" lazy="proxy" fetch="select">
            <column name="SENSEWARE_INSTALL_ID" not-null="false" sql-type="INTEGER"/>
        </many-to-one>
        <many-to-one name="object" class="com.oatsystems.udm.logicalObj.LogicalObjectImpl" foreign-key="OBJ_ASSN_FK9" lazy="proxy" fetch="select">
            <column name="OBJECT_ID" not-null="false" sql-type="INTEGER"/>
        </many-to-one>
        <many-to-one name="assnRelation" class="com.oatsystems.udm.logicalHier.AssnRelationImpl" foreign-key="OBJ_ASSN_FK7" lazy="proxy" fetch="select">
            <column name="ASSN_RELATION_ID" not-null="false" sql-type="INTEGER"/>
        </many-to-one>
        <many-to-one name="startAssnLocation" class="com.oatsystems.udm.physical.LocationImpl" foreign-key="OBJ_ASSN_FK5" lazy="proxy" fetch="select">
            <column name="START_ASSN_LOCATION_ID" not-null="false" sql-type="INTEGER"/>
        </many-to-one>
        <many-to-one name="parentLocation" class="com.oatsystems.udm.physical.LocationImpl" foreign-key="OBJ_ASSN_FK4" lazy="proxy" fetch="select">
            <column name="PARENT_LOCATION_ID" not-null="false" sql-type="INTEGER"/>
        </many-to-one>
        <many-to-one name="assnStartMethod" class="com.oatsystems.udm.logicalHier.AssnMethodImpl" foreign-key="OBJ_ASSN_FK1" lazy="proxy" fetch="select">
            <column name="ASSN_START_METHOD_ID" not-null="false" sql-type="INTEGER"/>
        </many-to-one>
    </class>
</hibernate-mapping>